{
  "tables": [
    {
      "id": "j1HT379tcIaTUxRyaFv_s",
      "name": "Departamentos",
      "x": -693.4370964258718,
      "y": -410.3532150955618,
      "locked": false,
      "fields": [
        {
          "name": "pk_DepartamentoId",
          "type": "INTEGER",
          "default": "",
          "check": "",
          "primary": true,
          "unique": true,
          "notNull": true,
          "increment": true,
          "comment": "",
          "id": "HcVLnkn5GaJkQWrUlrem7"
        },
        {
          "id": "_LMqGLW1-F4fEXZm63eTu",
          "name": "NombreDepartamento",
          "type": "VARCHAR",
          "default": "",
          "check": "",
          "primary": false,
          "unique": false,
          "notNull": true,
          "increment": false,
          "comment": "",
          "size": 80
        },
        {
          "id": "D8xuVkXmYjTmO_MwiU0z4",
          "name": "DescripcionDepartamento",
          "type": "VARCHAR",
          "default": "",
          "check": "",
          "primary": false,
          "unique": false,
          "notNull": true,
          "increment": false,
          "comment": "",
          "size": 255
        }
      ],
      "comment": "",
      "indices": [],
      "color": "#175e7a"
    },
    {
      "id": "bCtyToOK_FrNgBswDGWu4",
      "name": "Especialidades",
      "x": -692.4415235935643,
      "y": 394.0113243710183,
      "locked": false,
      "fields": [
        {
          "name": "pk_EspecialidadId",
          "type": "INTEGER",
          "default": "",
          "check": "",
          "primary": true,
          "unique": true,
          "notNull": true,
          "increment": true,
          "comment": "",
          "id": "HcVLnkn5GaJkQWrUlrem7"
        },
        {
          "id": "_LMqGLW1-F4fEXZm63eTu",
          "name": "NombreEspecialidad",
          "type": "VARCHAR",
          "default": "",
          "check": "",
          "primary": false,
          "unique": false,
          "notNull": true,
          "increment": false,
          "comment": "",
          "size": 80
        },
        {
          "id": "D8xuVkXmYjTmO_MwiU0z4",
          "name": "DescripcionEspecialidad",
          "type": "VARCHAR",
          "default": "",
          "check": "",
          "primary": false,
          "unique": false,
          "notNull": true,
          "increment": false,
          "comment": "",
          "size": 255
        }
      ],
      "comment": "",
      "indices": [],
      "color": "#175e7a"
    },
    {
      "id": "pTGdoZT__c_s61JQPzFp4",
      "name": "Doctores",
      "x": -698.6201220170609,
      "y": -178.84473868912647,
      "locked": false,
      "fields": [
        {
          "name": "pk_DoctoriId",
          "type": "INTEGER",
          "default": "",
          "check": "",
          "primary": true,
          "unique": true,
          "notNull": true,
          "increment": true,
          "comment": "",
          "id": "yH6WpqxEUbrzIig137Mxe"
        },
        {
          "id": "0JINhi3sqLwO1Rat644vr",
          "name": "NombreDoctor",
          "type": "VARCHAR",
          "default": "",
          "check": "",
          "primary": false,
          "unique": false,
          "notNull": true,
          "increment": false,
          "comment": "",
          "size": 80
        },
        {
          "id": "-i-ZiX4IPJ2OR8W2SbDTo",
          "name": "ApellidoDoctor",
          "type": "VARCHAR",
          "default": "",
          "check": "",
          "primary": false,
          "unique": false,
          "notNull": true,
          "increment": false,
          "comment": "",
          "size": 80
        },
        {
          "id": "S7GkTMeBr4wA-1gg6SVU1",
          "name": "EmailDoctor",
          "type": "VARCHAR",
          "default": "",
          "check": "",
          "primary": false,
          "unique": false,
          "notNull": true,
          "increment": false,
          "comment": "",
          "size": 80
        },
        {
          "id": "o9UXcwrp25RTL3W6XIMMf",
          "name": "TelefonoDoctor",
          "type": "VARCHAR",
          "default": "",
          "check": "",
          "primary": false,
          "unique": false,
          "notNull": true,
          "increment": false,
          "comment": "",
          "size": 30
        },
        {
          "id": "BSun3CShcPxovdz5ZT2Pw",
          "name": "fk_DepartamentoId",
          "type": "INTEGER",
          "default": "",
          "check": "",
          "primary": false,
          "unique": false,
          "notNull": true,
          "increment": false,
          "comment": "",
          "size": "",
          "values": []
        }
      ],
      "comment": "",
      "indices": [],
      "color": "#175e7a"
    },
    {
      "id": "UWg22OUqGZpYNezmfQtV8",
      "name": "DoctoresEspecialidades",
      "x": -676.1603444552425,
      "y": 196.9246166720657,
      "locked": false,
      "fields": [
        {
          "name": "fk_DoctorId",
          "type": "INTEGER",
          "default": "",
          "check": "",
          "primary": true,
          "unique": false,
          "notNull": true,
          "increment": false,
          "comment": "",
          "id": "cPILwMSmoWi_T2rjGM9WW"
        },
        {
          "id": "avLRzQJPN8c91ganFhrd7",
          "name": "fk_EspecialidadId",
          "type": "INTEGER",
          "default": "",
          "check": "",
          "primary": true,
          "unique": false,
          "notNull": true,
          "increment": false,
          "comment": "",
          "size": "",
          "values": []
        }
      ],
      "comment": "",
      "indices": [],
      "color": "#175e7a"
    },
    {
      "id": "VImKv8vSgAsTTVCFIeYnv",
      "name": "Pacientes",
      "x": 147.20862217902982,
      "y": -267.68827610409244,
      "locked": false,
      "fields": [
        {
          "name": "pk_PacienteiId",
          "type": "INTEGER",
          "default": "",
          "check": "",
          "primary": true,
          "unique": true,
          "notNull": true,
          "increment": true,
          "comment": "",
          "id": "yH6WpqxEUbrzIig137Mxe"
        },
        {
          "id": "0JINhi3sqLwO1Rat644vr",
          "name": "NombrePaciente",
          "type": "VARCHAR",
          "default": "",
          "check": "",
          "primary": false,
          "unique": false,
          "notNull": true,
          "increment": false,
          "comment": "",
          "size": 80
        },
        {
          "id": "-i-ZiX4IPJ2OR8W2SbDTo",
          "name": "ApellidoPaciente",
          "type": "VARCHAR",
          "default": "",
          "check": "",
          "primary": false,
          "unique": false,
          "notNull": true,
          "increment": false,
          "comment": "",
          "size": 80
        },
        {
          "id": "S7GkTMeBr4wA-1gg6SVU1",
          "name": "EmailPaciente",
          "type": "VARCHAR",
          "default": "",
          "check": "",
          "primary": false,
          "unique": false,
          "notNull": true,
          "increment": false,
          "comment": "",
          "size": 80
        },
        {
          "id": "o9UXcwrp25RTL3W6XIMMf",
          "name": "TelefonoPaciente",
          "type": "VARCHAR",
          "default": "",
          "check": "",
          "primary": false,
          "unique": false,
          "notNull": true,
          "increment": false,
          "comment": "",
          "size": 30
        },
        {
          "id": "q7Z2bEZ8kFniAsEduROAW",
          "name": "DireccionPaciente",
          "type": "VARCHAR",
          "default": "",
          "check": "",
          "primary": false,
          "unique": false,
          "notNull": true,
          "increment": false,
          "comment": "",
          "size": 150
        },
        {
          "id": "ub6gtm6fpfPIzWKg18O9c",
          "name": "FechaNacimientoPaciente",
          "type": "DATE",
          "default": "",
          "check": "",
          "primary": false,
          "unique": false,
          "notNull": true,
          "increment": false,
          "comment": "",
          "size": "",
          "values": []
        }
      ],
      "comment": "",
      "indices": [],
      "color": "#175e7a"
    },
    {
      "id": "zdTt6vyhH7Wa09aMM_8ht",
      "name": "HistoriaClinica",
      "x": 264.558800345535,
      "y": 135.59214717633083,
      "locked": false,
      "fields": [
        {
          "name": "pk_HistoriaClinicaId",
          "type": "INTEGER",
          "default": "",
          "check": "",
          "primary": true,
          "unique": true,
          "notNull": true,
          "increment": true,
          "comment": "",
          "id": "eD4IoVIj-j0Qi9Rv_MGzi"
        },
        {
          "id": "0rWClwnALG_qJs-iuRZdq",
          "name": "FechaAperturaHistoria",
          "type": "DATE",
          "default": "",
          "check": "",
          "primary": false,
          "unique": false,
          "notNull": true,
          "increment": false,
          "comment": "",
          "size": "",
          "values": []
        },
        {
          "id": "LvK8mLUyRMX0zB5ujwJGr",
          "name": "Observaciones",
          "type": "LONGTEXT",
          "default": "",
          "check": "",
          "primary": false,
          "unique": false,
          "notNull": true,
          "increment": false,
          "comment": "",
          "size": 65535
        },
        {
          "id": "Ldj9UiBvmnnEGXjPrHv5m",
          "name": "fk_PacienteId",
          "type": "INTEGER",
          "default": "",
          "check": "",
          "primary": false,
          "unique": false,
          "notNull": true,
          "increment": false,
          "comment": "",
          "size": "",
          "values": []
        }
      ],
      "comment": "",
      "indices": [],
      "color": "#175e7a"
    },
    {
      "id": "4f3tEfVaOyXoIKrjEEJEQ",
      "name": "MotivosCita",
      "x": -390.23009934132375,
      "y": 350.68770921066834,
      "locked": false,
      "fields": [
        {
          "name": "pk_Motivo_Id",
          "type": "INTEGER",
          "default": "",
          "check": "",
          "primary": true,
          "unique": true,
          "notNull": true,
          "increment": true,
          "comment": "",
          "id": "V-BXu4DHIapALYekbjOd9"
        },
        {
          "id": "cBc-7lNpj8lMToxt3Cnij",
          "name": "MotivoDescripcion",
          "type": "VARCHAR",
          "default": "",
          "check": "",
          "primary": false,
          "unique": false,
          "notNull": true,
          "increment": false,
          "comment": "",
          "size": 80
        }
      ],
      "comment": "",
      "indices": [],
      "color": "#175e7a"
    },
    {
      "id": "0icokxE4zh17m0vzMLmun",
      "name": "EstadosCita",
      "x": -162.04523809523783,
      "y": 360.3216580282907,
      "locked": false,
      "fields": [
        {
          "name": "pk_EstadoCita_Id",
          "type": "INTEGER",
          "default": "",
          "check": "",
          "primary": true,
          "unique": true,
          "notNull": true,
          "increment": true,
          "comment": "",
          "id": "V-BXu4DHIapALYekbjOd9"
        },
        {
          "id": "cBc-7lNpj8lMToxt3Cnij",
          "name": "EstadoCitaDescripcion",
          "type": "VARCHAR",
          "default": "",
          "check": "",
          "primary": false,
          "unique": false,
          "notNull": true,
          "increment": false,
          "comment": "",
          "size": 80
        }
      ],
      "comment": "",
      "indices": [],
      "color": "#175e7a"
    },
    {
      "id": "lCZ4Eq8k9_lB0sPsVwHrc",
      "name": "TiposCita",
      "x": 168.0724597775619,
      "y": 378.59398283122755,
      "locked": false,
      "fields": [
        {
          "name": "pk_TipoCita_Id",
          "type": "INTEGER",
          "default": "",
          "check": "",
          "primary": true,
          "unique": true,
          "notNull": true,
          "increment": true,
          "comment": "",
          "id": "V-BXu4DHIapALYekbjOd9"
        },
        {
          "id": "cBc-7lNpj8lMToxt3Cnij",
          "name": "TipoCitaDescripcion",
          "type": "VARCHAR",
          "default": "",
          "check": "",
          "primary": false,
          "unique": false,
          "notNull": true,
          "increment": false,
          "comment": "",
          "size": 80
        }
      ],
      "comment": "",
      "indices": [],
      "color": "#175e7a"
    },
    {
      "id": "6W-6ZEblxuLiTJYz48_Xd",
      "name": "Citas",
      "x": -229.55630601446938,
      "y": -372.34436076017687,
      "locked": false,
      "fields": [
        {
          "name": "pk_CitaId",
          "type": "INTEGER",
          "default": "",
          "check": "",
          "primary": true,
          "unique": true,
          "notNull": true,
          "increment": true,
          "comment": "",
          "id": "TNfJi_m_ps3RTadqerIve"
        },
        {
          "id": "rZj-Uhq8wJ_1UeMR_o_rD",
          "name": "FechaHoraCita",
          "type": "DATETIME",
          "default": "",
          "check": "",
          "primary": false,
          "unique": false,
          "notNull": true,
          "increment": false,
          "comment": "",
          "size": "",
          "values": []
        },
        {
          "id": "R9snE01s_02LpFiG5x0yC",
          "name": "fk_DoctorId",
          "type": "INTEGER",
          "default": "",
          "check": "",
          "primary": false,
          "unique": false,
          "notNull": true,
          "increment": false,
          "comment": "",
          "size": "",
          "values": []
        },
        {
          "id": "C3j1-BZAIIIxyyveZdcXP",
          "name": "fk_Pacienteid",
          "type": "INTEGER",
          "default": "",
          "check": "",
          "primary": false,
          "unique": false,
          "notNull": true,
          "increment": false,
          "comment": "",
          "size": "",
          "values": []
        },
        {
          "id": "VvF4w4vmS3YA7UfMDpoLU",
          "name": "fk_MotivoCitaId",
          "type": "INTEGER",
          "default": "",
          "check": "",
          "primary": false,
          "unique": false,
          "notNull": true,
          "increment": false,
          "comment": "",
          "size": "",
          "values": []
        },
        {
          "id": "jNcWo_w1lAYPDt-4qojCy",
          "name": "fk_EstadoCitaId",
          "type": "INTEGER",
          "default": "",
          "check": "",
          "primary": false,
          "unique": false,
          "notNull": true,
          "increment": false,
          "comment": "",
          "size": "",
          "values": []
        },
        {
          "id": "91zIi-g18UnVSVWPNwxNQ",
          "name": "fk_TipoCitaId",
          "type": "INTEGER",
          "default": "",
          "check": "",
          "primary": false,
          "unique": false,
          "notNull": true,
          "increment": false,
          "comment": "",
          "size": "",
          "values": []
        },
        {
          "id": "HbkZH7D0ajh1BxTCKpW1v",
          "name": "DiagnosticoCita",
          "type": "LONGTEXT",
          "default": "",
          "check": "",
          "primary": false,
          "unique": false,
          "notNull": true,
          "increment": false,
          "comment": "",
          "size": 65535
        }
      ],
      "comment": "",
      "indices": [],
      "color": "#175e7a"
    },
    {
      "id": "s4xPmKAQ4yKySz3WhJIiQ",
      "name": "Recetas",
      "x": -271.8843483425114,
      "y": -834.4974759745165,
      "locked": false,
      "fields": [
        {
          "name": "pk_RecetaId",
          "type": "INTEGER",
          "default": "",
          "check": "",
          "primary": true,
          "unique": true,
          "notNull": true,
          "increment": true,
          "comment": "",
          "id": "VTJUW3rbt-8AEQ252Vgm6"
        },
        {
          "id": "ddZN22apSpsAlS6SJrIdL",
          "name": "fk_CitaId",
          "type": "INTEGER",
          "default": "",
          "check": "",
          "primary": false,
          "unique": false,
          "notNull": true,
          "increment": false,
          "comment": "",
          "size": "",
          "values": []
        },
        {
          "id": "JJ53iMi3oEioLrmxpbsse",
          "name": "FechaReceta",
          "type": "DATE",
          "default": "",
          "check": "",
          "primary": false,
          "unique": false,
          "notNull": true,
          "increment": false,
          "comment": "",
          "size": "",
          "values": []
        },
        {
          "id": "Xw4QaGSF3hDmho0PnxJuN",
          "name": "ObsReceta",
          "type": "LONGTEXT",
          "default": "",
          "check": "",
          "primary": false,
          "unique": false,
          "notNull": true,
          "increment": false,
          "comment": "",
          "size": 65535
        }
      ],
      "comment": "",
      "indices": [],
      "color": "#175e7a"
    },
    {
      "id": "mVYZpsH8KQY4ly1inAbhs",
      "name": "Medicamentos",
      "x": 350.21045783392753,
      "y": -736.7520921066837,
      "locked": false,
      "fields": [
        {
          "name": "pk_MedicamentoId",
          "type": "INTEGER",
          "default": "",
          "check": "",
          "primary": true,
          "unique": true,
          "notNull": true,
          "increment": true,
          "comment": "",
          "id": "HcVLnkn5GaJkQWrUlrem7"
        },
        {
          "id": "_LMqGLW1-F4fEXZm63eTu",
          "name": "NombreMedicamento",
          "type": "VARCHAR",
          "default": "",
          "check": "",
          "primary": false,
          "unique": false,
          "notNull": true,
          "increment": false,
          "comment": "",
          "size": 80
        },
        {
          "id": "D8xuVkXmYjTmO_MwiU0z4",
          "name": "DescripcionMedicamento",
          "type": "VARCHAR",
          "default": "",
          "check": "",
          "primary": false,
          "unique": false,
          "notNull": true,
          "increment": false,
          "comment": "",
          "size": 255
        }
      ],
      "comment": "",
      "indices": [],
      "color": "#175e7a"
    },
    {
      "id": "fyov7tovB-R6tx6T-KlUJ",
      "name": "RecetasMedicamentos",
      "x": 71.0591782744841,
      "y": -720.4709129683617,
      "locked": false,
      "fields": [
        {
          "name": "fk_RecetaId",
          "type": "INTEGER",
          "default": "",
          "check": "",
          "primary": true,
          "unique": false,
          "notNull": true,
          "increment": false,
          "comment": "",
          "id": "5BrbHWSoLc4wSooF58qsO"
        },
        {
          "id": "NDdtrsHrzPGOw5rua48IP",
          "name": "fk_MedicamentoId",
          "type": "INTEGER",
          "default": "",
          "check": "",
          "primary": true,
          "unique": false,
          "notNull": true,
          "increment": false,
          "comment": "",
          "size": "",
          "values": []
        },
        {
          "id": "_TnHYrvYPyXYCx7zgEyfA",
          "name": "Dosis",
          "type": "VARCHAR",
          "default": "",
          "check": "",
          "primary": false,
          "unique": false,
          "notNull": true,
          "increment": false,
          "comment": "",
          "size": 100
        },
        {
          "id": "w_w_l99FjQlSIcCNcMe5G",
          "name": "Duracion",
          "type": "VARCHAR",
          "default": "",
          "check": "",
          "primary": false,
          "unique": false,
          "notNull": true,
          "increment": false,
          "comment": "",
          "size": 100
        }
      ],
      "comment": "",
      "indices": [],
      "color": "#175e7a"
    },
    {
      "id": "8b-YNCcyq_e1UA41mgk2X",
      "name": "PruebasDiagnosticas",
      "x": -582.0020462153116,
      "y": -838.8166639671741,
      "locked": false,
      "fields": [
        {
          "name": "pk_PruebaDiagnosticaId",
          "type": "INTEGER",
          "default": "",
          "check": "",
          "primary": true,
          "unique": true,
          "notNull": true,
          "increment": true,
          "comment": "",
          "id": "3KLyzVDs-7bO9387xHa2h"
        },
        {
          "id": "B1uQo1cgxkEkXRnS3bvP6",
          "name": "fk_CitaId",
          "type": "INTEGER",
          "default": "",
          "check": "",
          "primary": false,
          "unique": false,
          "notNull": true,
          "increment": false,
          "comment": "",
          "size": "",
          "values": []
        },
        {
          "id": "SweOQhk1k9z44yGxtQrzB",
          "name": "FechaPrueba",
          "type": "DATE",
          "default": "",
          "check": "",
          "primary": false,
          "unique": false,
          "notNull": true,
          "increment": false,
          "comment": "",
          "size": "",
          "values": []
        },
        {
          "id": "y__k16jRvE1aZcpesjbw7",
          "name": "Resultado",
          "type": "LONGTEXT",
          "default": "",
          "check": "",
          "primary": false,
          "unique": false,
          "notNull": true,
          "increment": false,
          "comment": "",
          "size": 65535
        },
        {
          "id": "cbAylTXwS0Q5CENrJgZ5o",
          "name": "fk_TipoPruebaId",
          "type": "INTEGER",
          "default": "",
          "check": "",
          "primary": false,
          "unique": false,
          "notNull": true,
          "increment": false,
          "comment": "",
          "size": "",
          "values": []
        }
      ],
      "comment": "",
      "indices": [],
      "color": "#175e7a"
    },
    {
      "id": "hU0EyXX0LAX9v_o368wS8",
      "name": "TiposPrueba",
      "x": -706.3946604038439,
      "y": -577.9377092106682,
      "locked": false,
      "fields": [
        {
          "name": "pk_TipoPruebaId",
          "type": "INTEGER",
          "default": "",
          "check": "",
          "primary": true,
          "unique": true,
          "notNull": true,
          "increment": true,
          "comment": "",
          "id": "w5WpmOJXFQQ8o9p2QNZrF"
        },
        {
          "id": "Y6eFk9kkgaN3NMdvnGWh8",
          "name": "DescripcionTipoPrueba",
          "type": "VARCHAR",
          "default": "",
          "check": "",
          "primary": false,
          "unique": false,
          "notNull": true,
          "increment": false,
          "comment": "",
          "size": 100
        }
      ],
      "comment": "",
      "indices": [],
      "color": "#175e7a"
    }
  ],
  "relationships": [
    {
      "startTableId": "pTGdoZT__c_s61JQPzFp4",
      "startFieldId": "BSun3CShcPxovdz5ZT2Pw",
      "endTableId": "j1HT379tcIaTUxRyaFv_s",
      "endFieldId": "HcVLnkn5GaJkQWrUlrem7",
      "cardinality": "many_to_one",
      "updateConstraint": "No action",
      "deleteConstraint": "No action",
      "name": "fk_Doctores_fk_DepartamentoId_Departamentos",
      "id": "pjvOpMBZdZm6W7U8wttem"
    },
    {
      "startTableId": "UWg22OUqGZpYNezmfQtV8",
      "startFieldId": "cPILwMSmoWi_T2rjGM9WW",
      "endTableId": "pTGdoZT__c_s61JQPzFp4",
      "endFieldId": "yH6WpqxEUbrzIig137Mxe",
      "cardinality": "many_to_one",
      "updateConstraint": "No action",
      "deleteConstraint": "No action",
      "name": "fk_DoctoresEspecialidades_fk_DoctorId_Doctores",
      "id": "6Fb1LOOeluclcDR763PT2"
    },
    {
      "startTableId": "UWg22OUqGZpYNezmfQtV8",
      "startFieldId": "avLRzQJPN8c91ganFhrd7",
      "endTableId": "bCtyToOK_FrNgBswDGWu4",
      "endFieldId": "HcVLnkn5GaJkQWrUlrem7",
      "cardinality": "many_to_one",
      "updateConstraint": "No action",
      "deleteConstraint": "No action",
      "name": "fk_DoctoresEspecialidades_fk_EspecialidadId_Especialidades",
      "id": "H94fK7dXV1aOYw7JNx9m8"
    },
    {
      "startTableId": "zdTt6vyhH7Wa09aMM_8ht",
      "startFieldId": "Ldj9UiBvmnnEGXjPrHv5m",
      "endTableId": "VImKv8vSgAsTTVCFIeYnv",
      "endFieldId": "yH6WpqxEUbrzIig137Mxe",
      "cardinality": "many_to_one",
      "updateConstraint": "No action",
      "deleteConstraint": "No action",
      "name": "fk_HistoriaClinica_fk_PacienteId_Pacientes",
      "id": "5m7XQL2G04ZuqnLXKBZzW"
    },
    {
      "startTableId": "6W-6ZEblxuLiTJYz48_Xd",
      "startFieldId": "R9snE01s_02LpFiG5x0yC",
      "endTableId": "pTGdoZT__c_s61JQPzFp4",
      "endFieldId": "yH6WpqxEUbrzIig137Mxe",
      "cardinality": "many_to_one",
      "updateConstraint": "No action",
      "deleteConstraint": "No action",
      "name": "fk_Citas_fk_DoctorId_Doctores",
      "id": "I3Fje6jvXCwIyjQTKPZ95"
    },
    {
      "startTableId": "6W-6ZEblxuLiTJYz48_Xd",
      "startFieldId": "C3j1-BZAIIIxyyveZdcXP",
      "endTableId": "VImKv8vSgAsTTVCFIeYnv",
      "endFieldId": "yH6WpqxEUbrzIig137Mxe",
      "cardinality": "many_to_one",
      "updateConstraint": "No action",
      "deleteConstraint": "No action",
      "name": "fk_Citas_fk_Pacienteid_Pacientes",
      "id": "l4srZrjyYBninIYDkHzAI"
    },
    {
      "startTableId": "6W-6ZEblxuLiTJYz48_Xd",
      "startFieldId": "VvF4w4vmS3YA7UfMDpoLU",
      "endTableId": "4f3tEfVaOyXoIKrjEEJEQ",
      "endFieldId": "V-BXu4DHIapALYekbjOd9",
      "cardinality": "many_to_one",
      "updateConstraint": "No action",
      "deleteConstraint": "No action",
      "name": "fk_Citas_fk_MotivoCitaId_MotivosCita",
      "id": "IG_P713c_dhPd3nOCoC8V"
    },
    {
      "startTableId": "6W-6ZEblxuLiTJYz48_Xd",
      "startFieldId": "jNcWo_w1lAYPDt-4qojCy",
      "endTableId": "0icokxE4zh17m0vzMLmun",
      "endFieldId": "V-BXu4DHIapALYekbjOd9",
      "cardinality": "many_to_one",
      "updateConstraint": "No action",
      "deleteConstraint": "No action",
      "name": "fk_Citas_fk_EstadoCitaId_EstadosCita",
      "id": "M45Z-N5KeR8yaUBAbnVv8"
    },
    {
      "startTableId": "6W-6ZEblxuLiTJYz48_Xd",
      "startFieldId": "91zIi-g18UnVSVWPNwxNQ",
      "endTableId": "lCZ4Eq8k9_lB0sPsVwHrc",
      "endFieldId": "V-BXu4DHIapALYekbjOd9",
      "cardinality": "many_to_one",
      "updateConstraint": "No action",
      "deleteConstraint": "No action",
      "name": "fk_Citas_fk_TipoCitaId_TiposCita",
      "id": "IgON1DL7rdUoZpK8E8pGw"
    },
    {
      "startTableId": "s4xPmKAQ4yKySz3WhJIiQ",
      "startFieldId": "ddZN22apSpsAlS6SJrIdL",
      "endTableId": "6W-6ZEblxuLiTJYz48_Xd",
      "endFieldId": "TNfJi_m_ps3RTadqerIve",
      "cardinality": "many_to_one",
      "updateConstraint": "No action",
      "deleteConstraint": "No action",
      "name": "fk_Recetas_fk_CitaId_Citas",
      "id": "t_uVvbfDeo9SNHUTj0Jor"
    },
    {
      "startTableId": "fyov7tovB-R6tx6T-KlUJ",
      "startFieldId": "5BrbHWSoLc4wSooF58qsO",
      "endTableId": "s4xPmKAQ4yKySz3WhJIiQ",
      "endFieldId": "VTJUW3rbt-8AEQ252Vgm6",
      "cardinality": "many_to_one",
      "updateConstraint": "No action",
      "deleteConstraint": "No action",
      "name": "fk_RecetasMedicamentos_fk_RecetaId_Recetas",
      "id": "Cfrpjs3rJ2fyDMdsNv3y9"
    },
    {
      "startTableId": "fyov7tovB-R6tx6T-KlUJ",
      "startFieldId": "NDdtrsHrzPGOw5rua48IP",
      "endTableId": "mVYZpsH8KQY4ly1inAbhs",
      "endFieldId": "HcVLnkn5GaJkQWrUlrem7",
      "cardinality": "many_to_one",
      "updateConstraint": "No action",
      "deleteConstraint": "No action",
      "name": "fk_RecetasMedicamentos_fk_MedicamentoId_Medicamentos",
      "id": "Yy1XkHfLp99Q5oKPvrWGb"
    },
    {
      "startTableId": "8b-YNCcyq_e1UA41mgk2X",
      "startFieldId": "B1uQo1cgxkEkXRnS3bvP6",
      "endTableId": "6W-6ZEblxuLiTJYz48_Xd",
      "endFieldId": "TNfJi_m_ps3RTadqerIve",
      "cardinality": "many_to_one",
      "updateConstraint": "No action",
      "deleteConstraint": "No action",
      "name": "fk_PruebasDiagnosticas_fk_CitaId_Citas",
      "id": "AMxyNrDOlY6YjPij981jx"
    },
    {
      "startTableId": "8b-YNCcyq_e1UA41mgk2X",
      "startFieldId": "cbAylTXwS0Q5CENrJgZ5o",
      "endTableId": "hU0EyXX0LAX9v_o368wS8",
      "endFieldId": "w5WpmOJXFQQ8o9p2QNZrF",
      "cardinality": "many_to_one",
      "updateConstraint": "No action",
      "deleteConstraint": "No action",
      "name": "fk_PruebasDiagnosticas_fk_TipoPruebaId_TiposPrueba",
      "id": "7a0e4uSK7nbdzhJZL6g7P"
    }
  ],
  "notes": [],
  "subjectAreas": [],
  "database": "mysql",
  "title": "0484.BDD.Sistema.Hospitalario"
}